dllist.py
httpcache.py
lrucache.py
memcachemap.py
setup.py
svccache.egg-info/PKG-INFO
svccache.egg-info/SOURCES.txt
svccache.egg-info/dependency_links.txt
svccache.egg-info/requires.txt
svccache.egg-info/top_level.txt
svccache.egg-info/zip-safe