Metadata-Version: 1.0
Name: svccache
Version: 0.1
Summary: Python caching utilities
Home-page: http://github.com/langloisjp/pysvccache
Author: Jean-Philippe Langlois
Author-email: jpl@jplanglois.com
License: MIT
Platform: UNKNOWN
